ctcloudsdkecs/__init__.py
ctcloudsdkecs/v2/__init__.py
ctcloudsdkecs/v2/ecs_async_client.py
ctcloudsdkecs/v2/ecs_client.py
ctcloudsdkecs/v2/model/__init__.py
ctcloudsdkecs/v2/model/add_server_group_member_request.py
ctcloudsdkecs/v2/model/add_server_group_member_request_body.py
ctcloudsdkecs/v2/model/add_server_group_member_response.py
ctcloudsdkecs/v2/model/associate_server_virtual_ip_option.py
ctcloudsdkecs/v2/model/associate_server_virtual_ip_request.py
ctcloudsdkecs/v2/model/associate_server_virtual_ip_request_body.py
ctcloudsdkecs/v2/model/associate_server_virtual_ip_response.py
ctcloudsdkecs/v2/model/attach_server_volume_option.py
ctcloudsdkecs/v2/model/attach_server_volume_request.py
ctcloudsdkecs/v2/model/attach_server_volume_request_body.py
ctcloudsdkecs/v2/model/attach_server_volume_response.py
ctcloudsdkecs/v2/model/batch_add_server_nic_option.py
ctcloudsdkecs/v2/model/batch_add_server_nics_request.py
ctcloudsdkecs/v2/model/batch_add_server_nics_request_body.py
ctcloudsdkecs/v2/model/batch_add_server_nics_response.py
ctcloudsdkecs/v2/model/batch_attach_sharable_volumes_option.py
ctcloudsdkecs/v2/model/batch_attach_sharable_volumes_request.py
ctcloudsdkecs/v2/model/batch_attach_sharable_volumes_request_body.py
ctcloudsdkecs/v2/model/batch_attach_sharable_volumes_response.py
ctcloudsdkecs/v2/model/batch_create_server_tags_request.py
ctcloudsdkecs/v2/model/batch_create_server_tags_request_body.py
ctcloudsdkecs/v2/model/batch_create_server_tags_response.py
ctcloudsdkecs/v2/model/batch_delete_server_nic_option.py
ctcloudsdkecs/v2/model/batch_delete_server_nics_request.py
ctcloudsdkecs/v2/model/batch_delete_server_nics_request_body.py
ctcloudsdkecs/v2/model/batch_delete_server_nics_response.py
ctcloudsdkecs/v2/model/batch_delete_server_tags_request.py
ctcloudsdkecs/v2/model/batch_delete_server_tags_request_body.py
ctcloudsdkecs/v2/model/batch_delete_server_tags_response.py
ctcloudsdkecs/v2/model/batch_reboot_servers_request.py
ctcloudsdkecs-0.0.1b0.dist-info/LICENSE
ctcloudsdkecs-0.0.1b0.dist-info/METADATA
ctcloudsdkecs-0.0.1b0.dist-info/WHEEL
ctcloudsdkecs-0.0.1b0.dist-info/top_level.txt
ctcloudsdkecs-0.0.1b0.dist-info/RECORD
